zappa_env/__init__.py
zappa_env/zappa_env.py
zappa_env-0.252.dist-info/LICENSE
zappa_env-0.252.dist-info/LICENSE.txt
zappa_env-0.252.dist-info/METADATA
zappa_env-0.252.dist-info/WHEEL
zappa_env-0.252.dist-info/top_level.txt
zappa_env-0.252.dist-info/RECORD
