Metadata-Version: 2.1
Name: zappa-env
Version: 0.252
Summary: Run Zappa commands with Python virtual environments.
Home-page: https://github.com/mrfleap/zappa-env
Author: Phillip Cutter
Author-email: mrfleap@gmail.com
License: MIT
Platform: UNKNOWN
Classifier: License :: OSI Approved :: MIT License
Classifier: Programming Language :: Python
Classifier: Programming Language :: Python :: 3
Classifier: Programming Language :: Python :: 3.6
Classifier: Programming Language :: Python :: Implementation :: CPython
Classifier: Programming Language :: Python :: Implementation :: PyPy
Requires-Python: >=3.6.0
Requires-Dist: zappa
